README.rst
setup.py
candonga/__init__.py
candonga/command.py
candonga/main.py
candonga.egg-info/PKG-INFO
candonga.egg-info/SOURCES.txt
candonga.egg-info/dependency_links.txt
candonga.egg-info/entry_points.txt
candonga.egg-info/namespace_packages.txt
candonga.egg-info/not-zip-safe
candonga.egg-info/pbr.json
candonga.egg-info/requires.txt
candonga.egg-info/top_level.txt