Metadata-Version: 1.1
Name: candonga
Version: 0.1
Summary: Candonga Framework
Home-page: https://github.com/rrobledo/candonga
Author: Raul Robledo
Author-email: raul.osvaldo.robledo@gmail.com
License: UNKNOWN
Download-URL: https://github.com/rrobledo/candonga.git
Platform: Any
Classifier: Development Status :: 3 - Alpha
Classifier: License :: OSI Approved :: MIT License
Classifier: Programming Language :: Python
Classifier: Programming Language :: Python :: 2
Classifier: Programming Language :: Python :: 2.7
Classifier: Programming Language :: Python :: 3
Classifier: Programming Language :: Python :: 3.2
Classifier: Intended Audience :: Developers
Classifier: Environment :: Console
